cookie_eater/__init__.py
cookie_eater/base.py
cookie_eater/chrome.py
cookie_eater/firefox.py
cookie_eater-1.0.0.dist-info/DESCRIPTION.rst
cookie_eater-1.0.0.dist-info/METADATA
cookie_eater-1.0.0.dist-info/RECORD
cookie_eater-1.0.0.dist-info/WHEEL
cookie_eater-1.0.0.dist-info/metadata.json
cookie_eater-1.0.0.dist-info/top_level.txt
test/__init__.py
test/test_browser.py
